praline/__init__.py
praline/cmd.py
praline/daemon.py
praline/component/__init__.py
praline/component/align.py
praline/component/blast.py
praline/component/demo.py
praline/component/msa.py
praline/component/preprofile.py
praline/component/profile.py
praline/component/tree.py
praline/component/workflow.py
praline/container/__init__.py
praline/container/align.py
praline/container/alphabet.py
praline/container/score.py
praline/container/sequence.py
praline/container/tree.py
praline/core/__init__.py
praline/core/component.py
praline/core/exception.py
praline/core/execution.py
praline/core/logging.py
praline/core/manager.py
praline/matrices/blosum100
praline/matrices/blosum30
praline/matrices/blosum35
praline/matrices/blosum40
praline/matrices/blosum45
praline/matrices/blosum50
praline/matrices/blosum55
praline/matrices/blosum60
praline/matrices/blosum62
praline/matrices/blosum65
praline/matrices/blosum70
praline/matrices/blosum75
praline/matrices/blosum80
praline/matrices/blosum85
praline/matrices/blosum90
praline/matrices/nucleotide
praline/util/__init__.py
praline/util/align.py
praline/util/cext.cpython-36m-darwin.so
praline/util/cli.py
praline/util/cluster.py
praline/util/legacy.py
praline/util/support.py
praline_aln-1.1.0.dist-info/LICENSE.txt
praline_aln-1.1.0.dist-info/METADATA
praline_aln-1.1.0.dist-info/WHEEL
praline_aln-1.1.0.dist-info/entry_points.txt
praline_aln-1.1.0.dist-info/top_level.txt
praline_aln-1.1.0.dist-info/RECORD
