Metadata-Version: 2.1
Name: praline-aln
Version: 1.1.0
Summary: PRALINE sequence alignment toolkit
Home-page: https://github.com/ibivu/PRALINE/
Author: Maurits Dijkstra
Author-email: mauritsdijkstra@gmail.com
License: GPLv2
Platform: UNKNOWN
Classifier: Development Status :: 5 - Production/Stable
Classifier: License :: OSI Approved :: GNU General Public License v2 (GPLv2)
Classifier: Environment :: Console
Classifier: Intended Audience :: Science/Research
Classifier: Programming Language :: Python :: 2.7
Classifier: Programming Language :: Python :: 3.6
Requires-Python: >=2.7,!=3.0.*,!=3.1.*,!=3.2.*,!=3.2.*,!=3.3.*,!=3.4.*
Requires-Dist: numpy (>=1.6.1)
Requires-Dist: falcon (>=0.3.0)
Requires-Dist: itsdangerous (>=0.24)
Requires-Dist: six (>=1.10.0)
